{"credit_default":[{"Payment":{"payday":"2016-07-08 00:00:00","data_id":"32904","category":"2","credit":"0","credit_date":"2016-07-08 00:00:00","counter_credit":"0","created":"2016-04-08 00:05:01","pers_pay":"2500","status":"no","payday_now":"2016-07-08 00:00:00","no_credit":"0"},"tech":{"username":"blevon"}},{"Payment":{"payday":"2016-07-08 18:47:15","data_id":"35398","category":"2","credit":"0","credit_date":"2016-07-08 18:47:15","counter_credit":"0","created":"2016-04-04 00:05:01","pers_pay":null,"status":null,"payday_now":"2016-06-05 00:05:02","no_credit":"0"},"tech":{"username":"edgardiana"}},{"Payment":{"payday":"2016-07-08 18:41:09","data_id":"35522","category":"2","credit":"0","credit_date":"2016-07-08 18:41:09","counter_credit":"0","created":"2016-03-17 00:05:01","pers_pay":null,"status":"11","payday_now":"2016-06-17 00:05:02","no_credit":"0"},"tech":{"username":"artakandryusha"}}],"no_credit":[{"Payment":{"payday":"2016-07-23 18:31:48","data_id":"29901","category":"2","credit":"0","credit_date":"2016-07-23 18:31:48","counter_credit":"0","created":"2016-04-07 00:05:02","pers_pay":null,"status":null,"payday_now":"2016-06-07 00:05:02","no_credit":"1"},"tech":{"username":"sergey95"}},{"Payment":{"payday":"2016-07-23 17:51:26","data_id":"30541","category":"2","credit":"0","credit_date":"2016-07-23 17:51:26","counter_credit":"0","created":"2016-04-05 00:05:01","pers_pay":null,"status":null,"payday_now":"2016-06-09 00:05:01","no_credit":"1"},"tech":{"username":"murad67"}},{"Payment":{"payday":"2016-07-23 00:00:00","data_id":"30481","category":"2","credit":"0","credit_date":"2016-07-23 18:28:56","counter_credit":"0","created":"2016-03-16 00:05:01","pers_pay":null,"status":"no","payday_now":"2016-06-23 00:00:00","no_credit":"1"},"tech":{"username":"abul95"}},{"Payment":{"payday":"2016-07-23 00:00:00","data_id":"31607","category":"2","credit":"0","credit_date":"2016-07-23 00:00:00","counter_credit":"0","created":"2016-03-22 00:05:01","pers_pay":null,"status":"no","payday_now":"2016-07-23 00:00:00","no_credit":"1"},"tech":{"username":"artash88"}},{"Payment":{"payday":"2016-07-23 18:06:16","data_id":"32765","category":"2","credit":"0","credit_date":"2016-07-23 18:06:16","counter_credit":"0","created":"2016-03-24 20:20:22","pers_pay":null,"status":"11","payday_now":"2016-06-20 00:05:01","no_credit":"1"},"tech":{"username":"ishkhannarek"}},{"Payment":{"payday":"2016-07-23 16:01:34","data_id":"31665","category":"2","credit":"0","credit_date":"2016-07-23 16:01:34","counter_credit":"0","created":"2016-04-03 00:05:02","pers_pay":null,"status":null,"payday_now":"2016-06-22 00:05:02","no_credit":"1"},"tech":{"username":"artavazdhayk"}},{"Payment":{"payday":"2016-07-23 00:00:00","data_id":"33863","category":"2","credit":"0","credit_date":"2016-07-24 15:33:03","counter_credit":"0","created":"2016-04-11 10:34:38","pers_pay":null,"status":"no","payday_now":"2016-06-23 00:00:00","no_credit":"1"},"tech":{"username":"gevorgzov"}},{"Payment":{"payday":"2016-07-23 19:08:44","data_id":"34006","category":"2","credit":"0","credit_date":"2016-07-23 19:08:44","counter_credit":"0","created":"2016-04-08 12:45:18","pers_pay":null,"status":"yes","payday_now":"2016-06-10 00:00:00","no_credit":"1"},"tech":{"username":"arsen93"}},{"Payment":{"payday":"2016-07-23 11:50:03","data_id":"31435","category":"2","credit":"0","credit_date":"2016-07-23 11:50:03","counter_credit":"0","created":"2016-03-26 00:05:01","pers_pay":null,"status":null,"payday_now":"2016-06-20 00:05:02","no_credit":"1"},"tech":{"username":"Vanik86"}}],"credit":[{"Payment":{"payday":"2016-07-23 12:20:52","data_id":"31987","category":"2","credit":"4","credit_date":"2016-07-19 12:20:52","counter_credit":"10","created":"2016-04-04 12:05:15","pers_pay":null,"status":null,"payday_now":"2016-06-08 00:05:01","no_credit":"0"},"tech":{"username":"khachik951"}},{"Payment":{"payday":"2016-07-23 19:12:20","data_id":"32258","category":"2","credit":"5","credit_date":"2016-07-18 19:12:20","counter_credit":"8","created":"2016-04-05 00:05:01","pers_pay":null,"status":"no","payday_now":"2016-07-08 00:00:00","no_credit":"0"},"tech":{"username":"karen1986"}},{"Payment":{"payday":"2016-07-23 16:27:56","data_id":"34269","category":"2","credit":"7","credit_date":"2016-07-16 16:27:56","counter_credit":"15","created":"2016-04-01 00:05:01","pers_pay":null,"status":null,"payday_now":"2016-06-01 00:05:02","no_credit":"0"},"tech":{"username":"artakgohar"}},{"Payment":{"payday":"2016-07-23 10:21:20","data_id":"35002","category":"2","credit":"5","credit_date":"2016-07-18 10:21:20","counter_credit":"9","created":"2016-04-10 00:05:02","pers_pay":null,"status":"11","payday_now":"2016-05-10 00:05:02","no_credit":"0"},"tech":{"username":"aziztornik"}},{"Payment":{"payday":"2016-07-23 17:24:42","data_id":"36198","category":"2","credit":"5","credit_date":"2016-07-18 17:24:42","counter_credit":"9","created":"2016-06-09 12:46:20","pers_pay":null,"status":"no","payday_now":"2016-07-09 00:00:00","no_credit":"0"},"tech":{"username":"sargisruzanna"}},{"Payment":{"payday":"2016-07-23 15:26:04","data_id":"36939","category":"2","credit":"4","credit_date":"2016-07-19 15:26:04","counter_credit":"11","created":"2016-07-06 17:46:42","pers_pay":null,"status":null,"payday_now":null,"no_credit":"0"},"tech":{"username":"innaelen"}}]}