{"credit_default":[{"Payment":{"payday":"2016-11-07 17:48:43","data_id":"29726","category":"2","credit":"0","credit_date":"2016-11-07 17:48:43","counter_credit":"0","created":"2016-04-07 00:05:02","pers_pay":"3500","status":"no","payday_now":"2016-07-07 00:00:00","no_credit":"0"},"tech":{"username":"karapet555"}},{"Payment":{"payday":"2016-11-07 15:40:37","data_id":"33412","category":"2","credit":"0","credit_date":"2016-11-07 15:40:37","counter_credit":"0","created":"2016-04-07 00:05:02","pers_pay":"3500","status":"no","payday_now":"2016-07-07 00:00:00","no_credit":"0"},"tech":{"username":"arsenaram"}},{"Payment":{"payday":"2016-11-07 00:00:00","data_id":"34527","category":"2","credit":"0","credit_date":"2016-11-07 00:00:00","counter_credit":"0","created":"2016-04-07 00:05:02","pers_pay":"3500","status":"no","payday_now":"2016-07-07 00:00:00","no_credit":"0"},"tech":{"username":"vminasyan"}},{"Payment":{"payday":"2016-11-07 18:13:31","data_id":"34877","category":"2","credit":"0","credit_date":"2016-11-07 18:13:31","counter_credit":"0","created":"2016-04-04 10:58:43","pers_pay":null,"status":"no","payday_now":"2016-07-08 00:00:00","no_credit":"0"},"tech":{"username":"geghayr"}},{"Payment":{"payday":"2016-11-07 17:26:26","data_id":"37201","category":"2","credit":"0","credit_date":"2016-11-07 17:26:26","counter_credit":"0","created":"2016-09-07 17:26:26","pers_pay":null,"status":null,"payday_now":null,"no_credit":"0"},"tech":{"username":"ghazarserine"}},{"Payment":{"payday":"2016-11-07 16:58:04","data_id":"37415","category":"2","credit":"0","credit_date":"2016-11-07 16:58:04","counter_credit":"0","created":"2016-10-06 16:09:28","pers_pay":null,"status":null,"payday_now":null,"no_credit":"0"},"tech":{"username":"login_user"}}],"no_credit":[{"Payment":{"payday":"2016-11-22 15:13:28","data_id":"29478","category":"2","credit":"0","credit_date":"2016-11-22 15:13:28","counter_credit":"0","created":"2016-04-11 00:05:01","pers_pay":null,"status":"no","payday_now":"2016-07-11 00:00:00","no_credit":"1"},"tech":{"username":"Gareginyan"}},{"Payment":{"payday":"2016-11-22 12:57:30","data_id":"32129","category":"2","credit":"0","credit_date":"2016-11-22 12:57:30","counter_credit":"0","created":"2016-02-07 00:05:01","pers_pay":null,"status":"11","payday_now":"2016-02-07 00:05:01","no_credit":"1"},"tech":{"username":"anahit61"}},{"Payment":{"payday":"2016-11-22 12:56:27","data_id":"31286","category":"2","credit":"1","credit_date":"2016-11-21 12:56:27","counter_credit":"0","created":"2016-03-15 00:05:01","pers_pay":null,"status":"11","payday_now":"2016-03-15 00:05:01","no_credit":"1"},"tech":{"username":"hayrapet2004"}},{"Payment":{"payday":"2016-11-22 14:48:55","data_id":"31080","category":"2","credit":"0","credit_date":"2016-11-22 14:48:55","counter_credit":"0","created":"2016-04-08 00:05:02","pers_pay":null,"status":"no","payday_now":"2016-07-14 00:00:00","no_credit":"1"},"tech":{"username":"hamlet1973"}},{"Payment":{"payday":"2016-11-22 15:43:14","data_id":"33998","category":"2","credit":"0","credit_date":"2016-11-22 15:43:14","counter_credit":"0","created":"2016-04-08 12:43:15","pers_pay":null,"status":"no","payday_now":"2016-07-14 00:00:00","no_credit":"1"},"tech":{"username":"davitmakich"}},{"Payment":{"payday":"2016-11-22 15:47:11","data_id":"34337","category":"2","credit":"0","credit_date":"2016-11-22 15:47:11","counter_credit":"0","created":"2016-03-12 00:05:01","pers_pay":null,"status":null,"payday_now":"2016-06-01 00:05:02","no_credit":"1"},"tech":{"username":"azizsartif"}}],"credit":[{"Payment":{"payday":"2016-11-22 15:23:29","data_id":"33009","category":"2","credit":"5","credit_date":"2016-11-17 15:23:29","counter_credit":"8","created":"2016-04-11 16:37:12","pers_pay":null,"status":"11","payday_now":"2016-06-30 00:05:01","no_credit":"0"},"tech":{"username":"haykmeruj"}},{"Payment":{"payday":"2016-11-22 15:45:24","data_id":"31252","category":"2","credit":"1","credit_date":"2016-11-21 15:45:24","counter_credit":"15","created":"2016-04-14 00:05:01","pers_pay":null,"status":null,"payday_now":"2016-06-22 00:05:02","no_credit":"0"},"tech":{"username":"anan9917"}}]}