{"credit_default":[{"Payment":{"payday":"2017-01-29 14:45:46","data_id":"31145","category":"2","credit":"0","credit_date":"2017-01-28 14:45:46","counter_credit":"1","created":"2016-04-07 00:05:02","pers_pay":"3000","status":"11","payday_now":"2016-05-07 00:05:01","no_credit":"0"},"tech":{"username":"sanser"}},{"Payment":{"payday":"2017-01-29 00:00:00","data_id":"31716","category":"2","credit":"0","credit_date":"2017-01-29 00:00:00","counter_credit":"0","created":"2016-03-26 00:05:01","pers_pay":null,"status":"no","payday_now":"2016-06-29 00:00:00","no_credit":"0"},"tech":{"username":"volodia38"}},{"Payment":{"payday":"2017-01-29 19:08:38","data_id":"32033","category":"2","credit":"0","credit_date":"2017-01-28 19:08:38","counter_credit":"1","created":"2016-03-28 00:05:01","pers_pay":null,"status":"11","payday_now":"2016-06-28 00:05:01","no_credit":"0"},"tech":{"username":"baregham64"}},{"Payment":{"payday":"2017-01-29 00:05:01","data_id":"32470","category":"2","credit":"0","credit_date":"2017-01-28 00:05:01","counter_credit":"1","created":"2016-03-28 00:05:01","pers_pay":null,"status":"11","payday_now":"2016-06-28 00:05:01","no_credit":"0"},"tech":{"username":"arman019"}},{"Payment":{"payday":"2017-01-29 00:05:01","data_id":"32289","category":"2","credit":"0","credit_date":"2017-01-29 00:05:01","counter_credit":"0","created":"2016-03-23 00:05:01","pers_pay":null,"status":"11","payday_now":"2016-06-29 00:05:01","no_credit":"0"},"tech":{"username":"anastasia"}},{"Payment":{"payday":"2017-01-29 19:08:39","data_id":"32564","category":"2","credit":"0","credit_date":"2017-01-28 19:08:39","counter_credit":"1","created":"2016-02-27 10:04:53","pers_pay":null,"status":"11","payday_now":"2016-06-07 00:05:01","no_credit":"0"},"tech":{"username":"haruttigran"}},{"Payment":{"payday":"2017-01-29 00:00:00","data_id":"34224","category":"2","credit":"0","credit_date":"2017-01-29 00:00:00","counter_credit":"0","created":"2016-03-29 00:05:02","pers_pay":null,"status":"no","payday_now":"2016-06-29 00:00:00","no_credit":"0"},"tech":{"username":"geghamzorik"}},{"Payment":{"payday":"2017-01-29 16:19:42","data_id":"34252","category":"2","credit":"0","credit_date":"2017-01-29 16:19:42","counter_credit":"0","created":"2016-03-28 00:05:01","pers_pay":null,"status":"11","payday_now":"2016-06-28 00:05:01","no_credit":"0"},"tech":{"username":"alenvera"}},{"Payment":{"payday":"2017-01-29 18:35:56","data_id":"34358","category":"2","credit":"0","credit_date":"2017-01-29 18:35:56","counter_credit":"0","created":"2016-04-12 00:05:01","pers_pay":null,"status":"11","payday_now":"2016-06-08 00:05:01","no_credit":"0"},"tech":{"username":"rustamgar"}},{"Payment":{"payday":"2017-01-29 17:18:48","data_id":"29125","category":"2","credit":"0","credit_date":"2017-01-29 17:18:48","counter_credit":"0","created":"2016-03-28 00:05:01","pers_pay":null,"status":"11","payday_now":"2016-06-28 00:05:01","no_credit":"0"},"tech":{"username":"Lyova55"}},{"Payment":{"payday":"2017-01-29 18:34:57","data_id":"34916","category":"2","credit":"0","credit_date":"2017-01-28 18:34:57","counter_credit":"1","created":"2016-03-28 00:05:01","pers_pay":null,"status":"11","payday_now":"2016-06-28 00:05:01","no_credit":"0"},"tech":{"username":"gagikevgenia"}},{"Payment":{"payday":"2017-01-29 17:26:30","data_id":"35148","category":"2","credit":"0","credit_date":"2017-01-29 17:26:30","counter_credit":"0","created":"2016-03-25 00:05:01","pers_pay":null,"status":"11","payday_now":"2016-06-27 00:05:01","no_credit":"0"},"tech":{"username":"datodav"}},{"Payment":{"payday":"2017-01-29 15:21:13","data_id":"35192","category":"2","credit":"0","credit_date":"2017-01-29 15:21:13","counter_credit":"0","created":"2016-03-29 00:05:02","pers_pay":null,"status":"11","payday_now":"2016-06-29 00:05:01","no_credit":"0"},"tech":{"username":"khachaturhayk"}},{"Payment":{"payday":"2017-01-29 16:23:15","data_id":"31177","category":"2","credit":"0","credit_date":"2017-01-28 16:23:15","counter_credit":"1","created":"2016-03-28 18:19:10","pers_pay":null,"status":"11","payday_now":"2016-06-28 00:05:01","no_credit":"0"},"tech":{"username":"vaghul11"}},{"Payment":{"payday":"2017-01-29 12:55:25","data_id":"29008","category":"2","credit":"0","credit_date":"2017-01-28 12:55:25","counter_credit":"1","created":"2016-04-14 00:05:01","pers_pay":null,"status":"11","payday_now":"2016-06-28 17:54:53","no_credit":"0"},"tech":{"username":"Manuk1985"}}],"no_credit":[{"Payment":{"payday":"2017-02-13 14:04:44","data_id":"29015","category":"2","credit":"0","credit_date":"2017-02-12 14:04:44","counter_credit":"1","created":"2016-03-03 19:56:39","pers_pay":null,"status":"11","payday_now":"2016-03-03 19:56:39","no_credit":"1"},"tech":{"username":"tumo"}},{"Payment":{"payday":"2017-02-13 19:28:45","data_id":"29776","category":"2","credit":"0","credit_date":"2017-02-13 19:28:45","counter_credit":"0","created":"2016-03-25 12:18:17","pers_pay":null,"status":"no","payday_now":"2016-07-04 00:00:00","no_credit":"1"},"tech":{"username":"hrant1985"}},{"Payment":{"payday":"2017-02-13 19:06:01","data_id":"32048","category":"2","credit":"0","credit_date":"2017-02-13 19:06:01","counter_credit":"0","created":"2016-04-09 00:05:02","pers_pay":null,"status":"no","payday_now":"2016-07-09 00:00:00","no_credit":"1"},"tech":{"username":"timofey"}},{"Payment":{"payday":"2017-02-13 17:58:16","data_id":"32665","category":"2","credit":"0","credit_date":"2017-02-12 17:58:16","counter_credit":"1","created":"2016-03-16 00:05:01","pers_pay":null,"status":"no","payday_now":"2017-01-14 10:32:41","no_credit":"1"},"tech":{"username":"yurakima"}},{"Payment":{"payday":"2017-02-13 14:16:55","data_id":"30549","category":"2","credit":"0","credit_date":"2017-02-13 14:16:55","counter_credit":"0","created":"2016-04-04 12:56:10","pers_pay":null,"status":"11","payday_now":"2016-06-09 00:05:01","no_credit":"1"},"tech":{"username":"luna777"}},{"Payment":{"payday":"2017-02-13 18:20:53","data_id":"32997","category":"2","credit":"0","credit_date":"2017-02-13 18:20:53","counter_credit":"0","created":"2015-06-03 10:06:52","pers_pay":null,"status":"11","payday_now":"2015-06-03 10:06:52","no_credit":"1"},"tech":{"username":"andhrach"}},{"Payment":{"payday":"2017-02-13 20:11:34","data_id":"33269","category":"2","credit":"0","credit_date":"2017-02-13 20:11:34","counter_credit":"0","created":"2016-04-09 00:05:02","pers_pay":null,"status":"no","payday_now":"2016-07-09 00:00:00","no_credit":"1"},"tech":{"username":"alikanush"}},{"Payment":{"payday":"2017-02-13 12:37:18","data_id":"30982","category":"2","credit":"1","credit_date":"2017-02-11 12:37:18","counter_credit":"1","created":"2016-04-12 00:05:01","pers_pay":null,"status":"11","payday_now":"2016-06-23 00:05:02","no_credit":"1"},"tech":{"username":"murad53"}},{"Payment":{"payday":"2017-02-13 12:35:51","data_id":"34809","category":"2","credit":"2","credit_date":"2017-02-11 12:35:51","counter_credit":"0","created":"2016-03-18 00:05:01","pers_pay":null,"status":"11","payday_now":"2016-06-28 10:48:12","no_credit":"1"},"tech":{"username":"valodvili"}},{"Payment":{"payday":"2017-02-13 12:36:03","data_id":"35129","category":"2","credit":"2","credit_date":"2017-02-11 12:36:03","counter_credit":"0","created":"2016-03-27 00:05:01","pers_pay":null,"status":"11","payday_now":"2016-06-08 00:05:01","no_credit":"1"},"tech":{"username":"zoyarustam"}},{"Payment":{"payday":"2017-02-13 10:56:57","data_id":"31435","category":"2","credit":"2","credit_date":"2017-02-11 10:56:57","counter_credit":"0","created":"2016-03-26 00:05:01","pers_pay":null,"status":null,"payday_now":"2016-06-20 00:05:02","no_credit":"1"},"tech":{"username":"Vanik86"}},{"Payment":{"payday":"2017-02-13 16:17:20","data_id":"35594","category":"2","credit":"0","credit_date":"2017-02-12 16:17:20","counter_credit":"1","created":"2016-03-25 00:05:01","pers_pay":null,"status":"11","payday_now":"2016-06-25 00:05:02","no_credit":"1"},"tech":{"username":"aniargam"}}],"credit":[{"Payment":{"payday":"2017-02-13 10:49:24","data_id":"31900","category":"2","credit":"4","credit_date":"2017-02-09 10:49:24","counter_credit":"6","created":"2016-03-19 00:05:01","pers_pay":null,"status":"11","payday_now":"2016-06-19 00:05:02","no_credit":"0"},"tech":{"username":"armgrig"}},{"Payment":{"payday":"2017-02-13 12:46:48","data_id":"34308","category":"2","credit":"5","credit_date":"2017-02-07 12:46:48","counter_credit":"1","created":"2016-02-26 00:05:01","pers_pay":null,"status":"11","payday_now":"2016-02-26 00:05:01","no_credit":"0"},"tech":{"username":"colakanna"}},{"Payment":{"payday":"2017-02-13 16:42:56","data_id":"35209","category":"2","credit":"2","credit_date":"2017-02-11 16:42:56","counter_credit":"11","created":"2016-03-15 00:05:01","pers_pay":null,"status":"11","payday_now":"2016-06-21 00:05:02","no_credit":"0"},"tech":{"username":"vitalalina"}},{"Payment":{"payday":"2017-02-13 10:48:16","data_id":"37367","category":"2","credit":"2","credit_date":"2017-02-11 10:48:16","counter_credit":"6","created":"2016-09-30 15:36:26","pers_pay":null,"status":null,"payday_now":null,"no_credit":"0"},"tech":{"username":"arpineluto"}},{"Payment":{"payday":"2017-02-13 13:13:13","data_id":"37452","category":"2","credit":"5","credit_date":"2017-02-08 13:13:13","counter_credit":"0","created":"2016-10-11 18:35:56","pers_pay":null,"status":null,"payday_now":null,"no_credit":"0"},"tech":{"username":"derenikmariam"}}]}